Metadata-Version: 2.1
Name: MYPRACT
Version: 0.0.1
Summary: this is a trial package used for calculation.
Home-page: 
Author: ARYAN SAMSUKHA
Author-email: ARYANSAMSUKHA@gmail.com
License: MIT
Platform: UNKNOWN
License-File: LICENCE.TXT
